osc_diagram/VERSION
osc_diagram/__init__.py
osc_diagram/main.py
osc_diagram-0.0.2.dist-info/LICENSE
osc_diagram-0.0.2.dist-info/METADATA
osc_diagram-0.0.2.dist-info/WHEEL
osc_diagram-0.0.2.dist-info/entry_points.txt
osc_diagram-0.0.2.dist-info/top_level.txt
osc_diagram-0.0.2.dist-info/RECORD
