Metadata-Version: 2.1
Name: osc-diagram
Version: 0.0.2
Summary: Outscale Gateway python SDK
Home-page: https://github.com/outscale-mgo/osc-diagram
Author: Outscal SAS
Author-email: opensource@outscale.com
Classifier: Programming Language :: Python :: 3
Classifier: License :: OSI Approved :: BSD License
Classifier: Operating System :: OS Independent
License-File: LICENSE
Requires-Dist: osc-sdk-python >=0.22.0
Requires-Dist: diagrams >=0.23.3
